[
	{"id": "407724585358852107", "name": "ExRaidPushers",
		"invite": "https://discord.gg/Wmwn8qp",
			"dateChecked": "20191012", "notes": "NEW, Spoofing, Active → 4k+"
	},
	{"id": "403210914612117506", "name": "PoGoConnection",
		"invite": "https://discord.gg/pZMGHcw",
			"dateChecked": "20191012", "notes": "NEW, Spoofing, Active → 6k+ ► TEAM ROLE"
	},
	{"id": "575393326228832271", "name": "PokeGoHack",
		"invite": "https://discord.gg/FJdWuPA ",
			"dateChecked": "20191012", "notes": "NEW, Spoofing, Active → 11k+"
	},
	{"id": "355390518391341056", "name": "PokeGoFam",
		"invite": "https://discord.gg/eUZEjAZ",
			"dateChecked": "20191012", "notes": "NEW, Spoofing, Active → 7k+"
	},
	{"id": "493887372522684451", "name": "iTools",
		"invite": "https://discord.gg/XF6vqZH",
			"dateChecked": "20191012", "notes": "NEW, Spoofing, Active → 4k+"
	},
	{"id": "642092173805879327", "name": "RocketHQ",
		"invite": "https://discord.gg/NkXfeTS",
			"dateChecked": "20191012", "notes": "NEW, Spoofing, Active → 7k+ ► TEAM ROLE"
	},
	{"id": "465816079554445332", "name": "iSpoofer",
		"invite": "https://discord.gg/pvQwqSe",
			"dateChecked": "20191012", "notes": "NEW, Spoofing, Active → 15.5k+"
	},
	{"id": "449254623438700544", "name": "PokeGoCoords",
		"invite": "https://discord.gg/jme4kjz",
			"dateChecked": "20191012", "notes": "NEW, Spoofing, Active → 9.5k+ ► TEAM ROLE"
	},
	{"id": "601395806775410712", "name": "PoGoHub",
		"invite": "https://discord.gg/6mbFTnX",
			"dateChecked": "20191012", "notes": "NEW, Spoofing, Active → 5.5k+ ► TEAM ROLE"
	},
	{"id": "622439771792474112", "name": "PoGoCDC",
		"invite": "https://discord.gg/9sr5fvQ",
			"dateChecked": "20191012", "notes": "NEW, Spoofing, Active → 2.5k+ ► TEAM ROLE"
	},
	
	
    {"id": "252776251708801024", "name": "PokeDex100",
		"invite": "https://discord.gg/Pokedex100",
			"dateChecked": "20191012", "notes": "Spoofing, Active → 240K+"
	},
	{"id": "271392134169493505", "name": "PokeXperience",
		"invite": "https://discord.gg/VHzfGzz",
			"dateChecked": "20191012", "notes": "Spoofing, Active → 171.5k+"
	},
	{"id": "211524693319090177", "name": "PokeSnipers",
		"invite": "https://discord.gg/pokesnipers",
			"dateChecked": "20191012", "notes": "Spoofing, Active → 140k+"
	},
	{"id": "256755952882024451", "name": "Catch'EmAll",
		"invite": "https://discord.gg/mAz9dQT",
			"dateChecked": "20191012", "notes": "Spoofing, Active → 43K+ ► RULES AND TEAM ROLE"
	},
	{"id": "230782016675774464", "name": "Articuno's Lair",
		"invite": "https://discord.gg/KMqMN23",
			"dateChecked": "20191012", "notes": "Spoofing, Active → 12.5K+"
	},
	{"id": "329745626549977088", "name": "GoRaiders",
		"invite": "https://discord.gg/fchWsyA",
			"dateChecked": "20191012", "notes": "Spoofing, Active → 6.5k+"
	},
	{"id": "245525908847329280", "name": "DiscPokeSnipers",
		"invite": "https://discord.gg/eZJZDE7",
			"dateChecked": "20191012", "notes": "Spoofing, Dead → DEAD 4.5k+"
	},
	{"id": "264132120337711105", "name": "OuDaPoke",
		"invite": "https://discord.gg/gPpBwAv",
			"dateChecked": "20191012", "notes": "Spoofing, Active → 4k+"
	},
	{"id": "405438758884999169", "name": "LoveGoIV100",
		"invite": "https://discord.gg/yrMrz5F",
			"dateChecked": "20191012", "notes": "Spoofing, Active → 8k+"
	},
	{"id": "332093891807412226", "name": "PokeGoClub",
		"invite": "https://discord.gg/rtEnd4W",
			"dateChecked": "20191012", "notes": "Spoofing, Little Activity → 5.5K+"
	},
	{"id": "314469632759169024", "name": "PokeMurph",
		"invite": "https://discord.gg/Rk2DYyG",
			"dateChecked": "20191012", "notes": "Spoofing, Little Activity → 3K+"
	},
	{"id": "297839926970417152", "name": "PokeNoobs",
		"invite": "https://discord.gg/HeqAtNy",
			"dateChecked": "20191012", "notes": "Spoofing, Little Activity → 2k+"
	},
	{"id": "632655162875445258", "name": "iPoGo",
		"invite": "https://discord.com/invite/zAfwRG7",
			"dateChecked": "20191012", "notes": "Spoofing, Little Activity → 2k+"
	},
	{"id": "213950622473388032", "name": "PogoNinja",
		"invite": "https://discord.gg/CtJP7WU",
			"dateChecked": "20191012", "notes": "Spoofing, Botting, Accounts for Sale"
	},
        {"id": "709832993660731514", "name": "PoGo Trainer Association",
		"invite": "https://discord.gg/gTYT4hy",
			"datChecked": "20200608", "notes": "Spoofing"
	},	
	{"id": "212977806819196938", "name": "CatchemPoGoBot",
		"invite": "https://discord.gg/pPwxX8Q",
			"dateChecked": "20191012", "notes": "Dead, Spoofing, Botting → DEAD 23k+"
	},
	{"id": "211288195462201347", "name": "PokeSnipersV2",
		"invite": "https://discord.gg/ueny2ej",
			"dateChecked": "20191012", "notes": "Dead, Spoofing, Little Activity, moved to Catch 'Em All → DEAD 19.5k+"
	},
	{"id": "208587704823316480", "name": "PokeFarmer",
		"invite": "https://discord.gg/Zw278sX",
			"dateChecked": "20191012", "notes": "Dead, Botting, Accounts for Sale → DEAD 6.5k+"
	},
	{"id": "208694020313055233", "name": "SytharixMarket",
		"invite": "https://discord.gg/hQpvJaE",
			"dateChecked": "20191012", "notes": "Dead, Botting, Accounts for Sale → DEAD 6.5k+"
	},
	{"id": "207436506833354754", "name": "HackEmon",
		"invite": "https://discord.gg/mMhuG6q",
			"dateChecked": "20191012", "notes": "Dead, Spoofing → DEAD 5.5k+"
	},
	{"id": "210496959973294081", "name": "BPGM",
		"invite": "https://discord.gg/SQMcuXc",
			"dateChecked": "20191012", "notes": "CONSIDER LEAVING, Dead, Botting, Accounts for Sale → DEAD 2K+"
	},
	{"id": "220608494934556672", "name": "GoMan.io",
		"invite": "https://discord.gg/GD43ZCG",
			"dateChecked": "20191012", "notes": "CONSIDER LEAVING, Dead, Botting, Accounts for Sale → DEAD 1.5k+"
	},
	{"id": "235509605994594304", "name": "PoGoSpoof",
		"invite": "https://discord.gg/HhY8FG2",
			"dateChecked": "20191012", "notes": "Dead, Spoofing, Botting → DEAD 1.5k+"
	},
	{"id": "208485545439920128", "name": "RocketBot",
		"invite": "https://discord.gg/FANTZCG",
			"dateChecked": "20191012", "notes": "CONSIDER LEAVING, Dead, Botting, Dead → DEAD 1.5k+"
	},
	{"id": "341581188567269376", "name": "UnownJay",
		"invite": "https://discord.gg/zBaPkAq",
			"dateChecked": "20191012", "notes": "CONSIDER LEAVING, Dead, Spoofing → DEAD 500+"
	},
	{"id": "335455302965002242", "name": "AccManager",
		"invite": "https://discord.gg/rkm4xhX",
			"dateChecked": "20191012", "notes": "CONSIDER LEAVING, Dead, Botting, Dead → DEAD 500+"
	},
	{"id": "301096455509245952", "name": "PokeGoScout",
		"invite": "https://discord.gg/PQpb6bN or https://discord.gg/6bEgfrW",
			"dateChecked": "20191012", "notes": "CONSIDER LEAVING, Dead, Spoofing, Dead, but live website → DEAD 500+"
	},
	{"id": "295165433340755970", "name": "PoGoMarketPlace",
		"invite": "https://discord.gg/ZdaJuqA",
			"dateChecked": "20191012", "notes": "CONSIDER LEAVING, Dead, Botting, Accounts for Sale → DEAD 500+"
	},
	{"id": "218144442345979906", "name": "PoGoCommunity",
		"invite": "https://discord.gg/CGYvRga",
			"dateChecked": "20191012", "notes": "CONSIDER LEAVING, Dead, Botting, Dead, Accounts for Sale → DEAD 500+"
	},
	{"id": "368059775008768000", "name": "PokeGOMaster",
		"invite": "https://discord.gg/bTfhuBc",
			"dateChecked": "20191012", "notes": "CONSIDER LEAVING, Dead, Botting, Accounts for Sale → DEAD 300+ ► Former PokeXen"
	},
	{"id": "306443147452612608", "name": "MrSnorlax",
		"invite": "https://discord.gg/8hB2TUs",
			"dateChecked": "20191012", "notes": "CONSIDER LEAVING, Dead, Spoofing, Active → DEAD 100+"
	},
	{"id": "603592836046389259", "name": "Pokemod",
                "invite": "https://discord.com/invite/Pokemod",
                "dateChecked": "20191012", "notes": "Very active spoofing server"
	}
]

